{
  "$schema": "https://frontmatter.codes/frontmatter.schema.json",
  "frontMatter.framework.id": "astro",
  "frontMatter.preview.host": "http://localhost:4321",
  "frontMatter.content.publicFolder": "public",
  "frontMatter.content.pageFolders": [
    {
      "title": "posts",
      "path": "[[workspace]]/src/content/posts"
    },
    {
      "title": "drafts",
      "path": "[[workspace]]/src/content/drafts"
    },
    {
      "title": "spec",
      "path": "[[workspace]]/src/content/spec"
    }
  ],
  "frontMatter.taxonomy.contentTypes": [
    {
      "name": "default",
      "pageBundle": false,
      "fields": [
        {
          "title": "title",
          "name": "title",
          "type": "string"
        },
        {
          "title": "description",
          "name": "description",
          "type": "string"
        },
        {
          "title": "published",
          "name": "published",
          "type": "datetime"
        },
        {
          "title": "draft",
          "name": "draft",
          "type": "draft"
        },
        {
          "title": "tags",
          "name": "tags",
          "type": "tags"
        },
        {
          "title": "category",
          "name": "category",
          "type": "categories"
        }
      ]
    }
  ]
}